{
    "homepage": "https://github.com/ginuerzh/gost",
    "description": "GO Simple Tunnel - a simple tunnel written in golang",
    "version": "2.10.1",
    "persist": "config.json",
    "pre_install": "New-Item -Path $dir -Name \"config.json\" -ItemType \"file\" -Value \"# 配置文件参考：https://docs.ginuerzh.xyz/gost/getting-started/\"",
    "architecture": {
        "64bit": {
            "bin": [
                [
                    "gost-windows-amd64.exe",
                    "gost",
                    "-C $persist_dir/config.json"
                ]
            ],
            "url": "https://github.com/ginuerzh/gost/releases/download/v2.10.1/gost-windows-amd64-2.10.1.zip",
            "hash": "e5e2b7c28ae0496df5ffc17a44ee528d24d4e3a996a8fadb008da018a6acc449"
        },
        "32bit": {
            "bin": [
                [
                    "gost-windows-386.exe",
                    "gost",
                    "-C $persist_dir/config.json"
                ]
            ],
            "url": "https://github.com/ginuerzh/gost/releases/download/v2.10.1/gost-windows-386-2.10.1.zip",
            "hash": "04f0610b477f5a086dad245fb1b707d4aa7e10aff66adca56fdec82ade8f3d2f"
        }
    },
    "checkver": "github",
    "autoupdate": {
        "architecture": {
            "64bit": {
                "url": "https://github.com/ginuerzh/gost/releases/download/v$version/gost-windows-amd64-$version.zip"
            },
            "32bit": {
                "url": "https://github.com/ginuerzh/gost/releases/download/v$version/gost-windows-386-$version.zip"
            }
        }
    }
}
